acs_student_attendance/__init__.py
acs_student_attendance/analysis.py
acs_student_attendance/log_parser.py
acs_student_attendance/shell.py
acs_student_attendance-1.0.4.dist-info/DESCRIPTION.rst
acs_student_attendance-1.0.4.dist-info/METADATA
acs_student_attendance-1.0.4.dist-info/RECORD
acs_student_attendance-1.0.4.dist-info/WHEEL
acs_student_attendance-1.0.4.dist-info/entry_points.txt
acs_student_attendance-1.0.4.dist-info/metadata.json
acs_student_attendance-1.0.4.dist-info/top_level.txt
