Metadata-Version: 2.0
Name: acs-student-attendance
Version: 1.0.4
Summary: Console app and Python API for analyzing and reporting the lab attendance of our ACS students
Home-page: https://github.com/petarmaric/acs_student_attendance
Author: Petar Maric
Author-email: petarmaric@uns.ac.rs
License: BSD
Platform: any
Classifier: Development Status :: 5 - Production/Stable
Classifier: Environment :: Console
Classifier: Intended Audience :: Developers
Classifier: Intended Audience :: Education
Classifier: License :: OSI Approved :: BSD License
Classifier: Operating System :: OS Independent
Classifier: Programming Language :: Python :: 2.7
Classifier: Topic :: Education
Classifier: Topic :: Utilities
Requires-Dist: PyYAML (~=3.11)
Requires-Dist: tablib (~=0.11.2)
